bc_stark_sdk-1.0.1.dist-info/METADATA
bc_stark_sdk-1.0.1.dist-info/WHEEL
bc_stark_sdk-1.0.1.dist-info/licenses/LICENSE
bc_stark_sdk.libs/libudev-e8fd959b.so.1
bc_stark_sdk/main_mod.pyi
bc_stark_sdk/main_mod.abi3.so
bc_stark_sdk-1.0.1.dist-info/RECORD
