Metadata-Version: 2.4
Name: bc_stark_sdk
Version: 1.0.1
Classifier: Programming Language :: Rust
Classifier: Programming Language :: Python :: Implementation :: CPython
Classifier: Programming Language :: Python :: Implementation :: PyPy
License-File: LICENSE
Summary: BrainCo Stark SDK
Author: BrainCo
License: 	
Requires-Python: >=3.8
Project-URL: Source Code, https://github.com/BrainCoTech/bc-stark-sdk
